google_datacatalog_rdbms_connector-0.12.2-py3.8-nspkg.pth
google/datacatalog_connectors/rdbms/__init__.py
google/datacatalog_connectors/rdbms/datacatalog_cli.py
google/datacatalog_connectors/rdbms/common/__init__.py
google/datacatalog_connectors/rdbms/common/constants.py
google/datacatalog_connectors/rdbms/prepare/__init__.py
google/datacatalog_connectors/rdbms/prepare/assembled_entry_factory.py
google/datacatalog_connectors/rdbms/prepare/datacatalog_entry_factory.py
google/datacatalog_connectors/rdbms/prepare/datacatalog_tag_factory.py
google/datacatalog_connectors/rdbms/prepare/datacatalog_tag_template_factory.py
google/datacatalog_connectors/rdbms/prepare/sql_objects/__init__.py
google/datacatalog_connectors/rdbms/prepare/sql_objects/sql_objects_assembled_entry_factory.py
google/datacatalog_connectors/rdbms/prepare/sql_objects/sql_objects_datacatalog_entry_factory.py
google/datacatalog_connectors/rdbms/prepare/sql_objects/sql_objects_datacatalog_tag_factory.py
google/datacatalog_connectors/rdbms/prepare/sql_objects/sql_objects_datacatalog_tag_template_factory.py
google/datacatalog_connectors/rdbms/prepare/sql_objects/sql_objects_metadata_config.py
google/datacatalog_connectors/rdbms/scrape/__init__.py
google/datacatalog_connectors/rdbms/scrape/base_metadata_enricher.py
google/datacatalog_connectors/rdbms/scrape/config.py
google/datacatalog_connectors/rdbms/scrape/metadata_enricher.py
google/datacatalog_connectors/rdbms/scrape/metadata_normalizer.py
google/datacatalog_connectors/rdbms/scrape/metadata_scraper.py
google/datacatalog_connectors/rdbms/scrape/query_assembler.py
google/datacatalog_connectors/rdbms/scrape/sql_objects/__init__.py
google/datacatalog_connectors/rdbms/scrape/sql_objects/sql_objects_metadata_normalizer.py
google/datacatalog_connectors/rdbms/scrape/sql_objects/sql_objects_metadata_scraper.py
google/datacatalog_connectors/rdbms/sync/__init__.py
google/datacatalog_connectors/rdbms/sync/datacatalog_synchronizer.py
google_datacatalog_rdbms_connector-0.12.2.dist-info/METADATA
google_datacatalog_rdbms_connector-0.12.2.dist-info/WHEEL
google_datacatalog_rdbms_connector-0.12.2.dist-info/namespace_packages.txt
google_datacatalog_rdbms_connector-0.12.2.dist-info/top_level.txt
google_datacatalog_rdbms_connector-0.12.2.dist-info/RECORD
