Metadata-Version: 2.1
Name: google-datacatalog-rdbms-connector
Version: 0.12.2
Summary: Commons library for ingesting RDBMS metadata into Google Cloud Data Catalog
Home-page: UNKNOWN
Author: Google LLC
License: UNKNOWN
Platform: Posix; MacOS X; Windows
Classifier: Development Status :: 4 - Beta
Classifier: Programming Language :: Python :: 3.7
Classifier: Operating System :: OS Independent
Classifier: Topic :: Internet
Requires-Dist: pandas (<1.2.0,>=1.1.4)
Requires-Dist: gcsfs
Requires-Dist: google-datacatalog-connectors-commons (>=0.6.0<0.7.0)
Requires-Dist: schema
